[
  {
    "perfIx": 124963,
    "movie": "4DX Spider-Man: Brand New Day",
    "venue": "GALA CINEMA (Langham Place)",
    "date": "2026-07-31",
    "time": "12:30 AM",
    "total": 121,
    "available": 109,
    "blocked": 0,
    "sold": 12,
    "gross": 2340,
    "price": 195,
    "last_updated": "2026-07-10 12:21:58 PM IST"
  },
  {
    "perfIx": 124969,
    "movie": "Movie 1012",
    "venue": "GALA CINEMA (Langham Place)",
    "date": "2026-07-31",
    "time": "12:35 AM",
    "total": 202,
    "available": 199,
    "blocked": 0,
    "sold": 3,
    "gross": 420,
    "price": 140,
    "last_updated": "2026-07-10 12:21:58 PM IST"
  },
  {
    "perfIx": 124859,
    "movie": "Spider-Man: Brand New Day",
    "venue": "MOViE MOViE Cityplaza (Taikoo Shing)",
    "date": "2026-07-31",
    "time": "10:15 AM",
    "total": 273,
    "available": 272,
    "blocked": 0,
    "sold": 1,
    "gross": 90,
    "price": 90,
    "last_updated": "2026-07-10 12:21:58 PM IST"
  },
  {
    "perfIx": 126194,
    "movie": "Movie 1055",
    "venue": "PREMIERE ELEMENTS",
    "date": "2026-07-31",
    "time": "10:20 AM",
    "total": 320,
    "available": 320,
    "blocked": 0,
    "sold": 0,
    "gross": 0,
    "price": 90,
    "last_updated": "2026-07-10 12:21:58 PM IST"
  },
  {
    "perfIx": 124970,
    "movie": "4DX Spider-Man: Brand New Day",
    "venue": "GALA CINEMA (Langham Place)",
    "date": "2026-07-31",
    "time": "10:45 AM",
    "total": 121,
    "available": 115,
    "blocked": 0,
    "sold": 6,
    "gross": 1050,
    "price": 175,
    "last_updated": "2026-07-10 12:21:58 PM IST"
  },
  {
    "perfIx": 125076,
    "movie": "Movie 1052",
    "venue": "B+ cinema apm (Kwun Tong)",
    "date": "2026-07-31",
    "time": "10:45 AM",
    "total": 290,
    "available": 290,
    "blocked": 0,
    "sold": 0,
    "gross": 0,
    "price": 80,
    "last_updated": "2026-07-10 12:21:58 PM IST"
  },
  {
    "perfIx": 124976,
    "movie": "Movie 1012",
    "venue": "GALA CINEMA (Langham Place)",
    "date": "2026-07-31",
    "time": "10:50 AM",
    "total": 202,
    "available": 196,
    "blocked": 0,
    "sold": 6,
    "gross": 540,
    "price": 90,
    "last_updated": "2026-07-10 12:21:58 PM IST"
  },
  {
    "perfIx": 125081,
    "movie": "4DX Spider-Man: Brand New Day",
    "venue": "B+ cinema apm (Kwun Tong)",
    "date": "2026-07-31",
    "time": "10:55 AM",
    "total": 52,
    "available": 43,
    "blocked": 0,
    "sold": 9,
    "gross": 1575,
    "price": 175,
    "last_updated": "2026-07-10 12:21:58 PM IST"
  },
  {
    "perfIx": 124858,
    "movie": "Spider-Man: Brand New Day",
    "venue": "MOViE MOViE Cityplaza (Taikoo Shing)",
    "date": "2026-07-31",
    "time": "1:00 PM",
    "total": 273,
    "available": 273,
    "blocked": 0,
    "sold": 0,
    "gross": 0,
    "price": 130,
    "last_updated": "2026-07-10 12:21:58 PM IST"
  },
  {
    "perfIx": 126195,
    "movie": "Movie 1055",
    "venue": "PREMIERE ELEMENTS",
    "date": "2026-07-31",
    "time": "1:10 PM",
    "total": 320,
    "available": 314,
    "blocked": 0,
    "sold": 6,
    "gross": 840,
    "price": 140,
    "last_updated": "2026-07-10 12:21:58 PM IST"
  },
  {
    "perfIx": 124971,
    "movie": "4DX Spider-Man: Brand New Day",
    "venue": "GALA CINEMA (Langham Place)",
    "date": "2026-07-31",
    "time": "1:30 PM",
    "total": 121,
    "available": 114,
    "blocked": 0,
    "sold": 7,
    "gross": 1365,
    "price": 195,
    "last_updated": "2026-07-10 12:21:58 PM IST"
  },
  {
    "perfIx": 125077,
    "movie": "Movie 1052",
    "venue": "B+ cinema apm (Kwun Tong)",
    "date": "2026-07-31",
    "time": "1:30 PM",
    "total": 290,
    "available": 286,
    "blocked": 0,
    "sold": 4,
    "gross": 480,
    "price": 120,
    "last_updated": "2026-07-10 12:21:58 PM IST"
  },
  {
    "perfIx": 124977,
    "movie": "Movie 1012",
    "venue": "GALA CINEMA (Langham Place)",
    "date": "2026-07-31",
    "time": "1:35 PM",
    "total": 202,
    "available": 198,
    "blocked": 0,
    "sold": 4,
    "gross": 560,
    "price": 140,
    "last_updated": "2026-07-10 12:21:58 PM IST"
  },
  {
    "perfIx": 125082,
    "movie": "4DX Spider-Man: Brand New Day",
    "venue": "B+ cinema apm (Kwun Tong)",
    "date": "2026-07-31",
    "time": "1:40 PM",
    "total": 52,
    "available": 44,
    "blocked": 0,
    "sold": 8,
    "gross": 1560,
    "price": 195,
    "last_updated": "2026-07-10 12:21:58 PM IST"
  },
  {
    "perfIx": 124857,
    "movie": "Spider-Man: Brand New Day",
    "venue": "MOViE MOViE Cityplaza (Taikoo Shing)",
    "date": "2026-07-31",
    "time": "3:45 PM",
    "total": 273,
    "available": 273,
    "blocked": 0,
    "sold": 0,
    "gross": 0,
    "price": 130,
    "last_updated": "2026-07-10 12:21:58 PM IST"
  },
  {
    "perfIx": 126196,
    "movie": "Movie 1055",
    "venue": "PREMIERE ELEMENTS",
    "date": "2026-07-31",
    "time": "4:00 PM",
    "total": 320,
    "available": 320,
    "blocked": 0,
    "sold": 0,
    "gross": 0,
    "price": 140,
    "last_updated": "2026-07-10 12:21:58 PM IST"
  },
  {
    "perfIx": 124972,
    "movie": "4DX Spider-Man: Brand New Day",
    "venue": "GALA CINEMA (Langham Place)",
    "date": "2026-07-31",
    "time": "4:15 PM",
    "total": 121,
    "available": 99,
    "blocked": 0,
    "sold": 22,
    "gross": 4290,
    "price": 195,
    "last_updated": "2026-07-10 12:21:58 PM IST"
  },
  {
    "perfIx": 125078,
    "movie": "Movie 1052",
    "venue": "B+ cinema apm (Kwun Tong)",
    "date": "2026-07-31",
    "time": "4:15 PM",
    "total": 290,
    "available": 290,
    "blocked": 0,
    "sold": 0,
    "gross": 0,
    "price": 120,
    "last_updated": "2026-07-10 12:21:58 PM IST"
  },
  {
    "perfIx": 124978,
    "movie": "Movie 1012",
    "venue": "GALA CINEMA (Langham Place)",
    "date": "2026-07-31",
    "time": "4:20 PM",
    "total": 202,
    "available": 197,
    "blocked": 0,
    "sold": 5,
    "gross": 700,
    "price": 140,
    "last_updated": "2026-07-10 12:21:58 PM IST"
  },
  {
    "perfIx": 125083,
    "movie": "4DX Spider-Man: Brand New Day",
    "venue": "B+ cinema apm (Kwun Tong)",
    "date": "2026-07-31",
    "time": "4:25 PM",
    "total": 52,
    "available": 45,
    "blocked": 0,
    "sold": 7,
    "gross": 1365,
    "price": 195,
    "last_updated": "2026-07-10 12:21:58 PM IST"
  },
  {
    "perfIx": 125205,
    "movie": "3D Spider-Man: Brand New Day",
    "venue": "MOViE MOViE Pacific Place (Admiralty)",
    "date": "2026-07-31",
    "time": "6:15 PM",
    "total": 113,
    "available": 112,
    "blocked": 0,
    "sold": 1,
    "gross": 165,
    "price": 165,
    "last_updated": "2026-07-10 12:21:58 PM IST"
  },
  {
    "perfIx": 124973,
    "movie": "4DX Spider-Man: Brand New Day",
    "venue": "GALA CINEMA (Langham Place)",
    "date": "2026-07-31",
    "time": "7:00 PM",
    "total": 121,
    "available": 95,
    "blocked": 0,
    "sold": 26,
    "gross": 5070,
    "price": 195,
    "last_updated": "2026-07-10 12:21:58 PM IST"
  },
  {
    "perfIx": 125079,
    "movie": "Movie 1052",
    "venue": "B+ cinema apm (Kwun Tong)",
    "date": "2026-07-31",
    "time": "7:00 PM",
    "total": 290,
    "available": 276,
    "blocked": 0,
    "sold": 14,
    "gross": 1680,
    "price": 120,
    "last_updated": "2026-07-10 12:21:58 PM IST"
  },
  {
    "perfIx": 124979,
    "movie": "Movie 1012",
    "venue": "GALA CINEMA (Langham Place)",
    "date": "2026-07-31",
    "time": "7:05 PM",
    "total": 202,
    "available": 177,
    "blocked": 0,
    "sold": 25,
    "gross": 3500,
    "price": 140,
    "last_updated": "2026-07-10 12:21:58 PM IST"
  },
  {
    "perfIx": 125084,
    "movie": "4DX Spider-Man: Brand New Day",
    "venue": "B+ cinema apm (Kwun Tong)",
    "date": "2026-07-31",
    "time": "7:10 PM",
    "total": 52,
    "available": 24,
    "blocked": 0,
    "sold": 28,
    "gross": 5460,
    "price": 195,
    "last_updated": "2026-07-10 12:21:58 PM IST"
  },
  {
    "perfIx": 124954,
    "movie": "3D Spider-Man: Brand New Day",
    "venue": "MY CINEMA YOHO MALL",
    "date": "2026-07-31",
    "time": "7:20 PM",
    "total": 98,
    "available": 89,
    "blocked": 0,
    "sold": 9,
    "gross": 1215,
    "price": 135,
    "last_updated": "2026-07-10 12:21:58 PM IST"
  },
  {
    "perfIx": 125142,
    "movie": "3D Spider-Man: Brand New Day",
    "venue": "B+ cinema MOKO (Mong Kok East)",
    "date": "2026-07-31",
    "time": "7:30 PM",
    "total": 140,
    "available": 127,
    "blocked": 0,
    "sold": 13,
    "gross": 1820,
    "price": 140,
    "last_updated": "2026-07-10 12:21:58 PM IST"
  },
  {
    "perfIx": 120997,
    "movie": "Ponsonbyland (EADF2026) ",
    "venue": "CINEMATHEQUE",
    "date": "2026-07-31",
    "time": "7:40 PM",
    "total": 119,
    "available": 101,
    "blocked": 0,
    "sold": 18,
    "gross": 1710,
    "price": 95,
    "last_updated": "2026-07-10 12:21:58 PM IST"
  },
  {
    "perfIx": 126227,
    "movie": "3D Spider-Man: Brand New Day",
    "venue": "PREMIERE ELEMENTS",
    "date": "2026-07-31",
    "time": "9:30 PM",
    "total": 116,
    "available": 114,
    "blocked": 0,
    "sold": 2,
    "gross": 290,
    "price": 145,
    "last_updated": "2026-07-10 12:21:58 PM IST"
  },
  {
    "perfIx": 124856,
    "movie": "Spider-Man: Brand New Day",
    "venue": "MOViE MOViE Cityplaza (Taikoo Shing)",
    "date": "2026-07-31",
    "time": "9:35 PM",
    "total": 273,
    "available": 261,
    "blocked": 0,
    "sold": 12,
    "gross": 1560,
    "price": 130,
    "last_updated": "2026-07-10 12:21:58 PM IST"
  },
  {
    "perfIx": 124871,
    "movie": "3D Spider-Man: Brand New Day",
    "venue": "PALACE ifc",
    "date": "2026-07-31",
    "time": "9:35 PM",
    "total": 94,
    "available": 94,
    "blocked": 0,
    "sold": 0,
    "gross": 0,
    "price": 165,
    "last_updated": "2026-07-10 12:21:58 PM IST"
  },
  {
    "perfIx": 125204,
    "movie": "3D Spider-Man: Brand New Day",
    "venue": "MOViE MOViE Pacific Place (Admiralty)",
    "date": "2026-07-31",
    "time": "9:35 PM",
    "total": 130,
    "available": 128,
    "blocked": 0,
    "sold": 2,
    "gross": 330,
    "price": 165,
    "last_updated": "2026-07-10 12:21:58 PM IST"
  },
  {
    "perfIx": 124974,
    "movie": "4DX Spider-Man: Brand New Day",
    "venue": "GALA CINEMA (Langham Place)",
    "date": "2026-07-31",
    "time": "9:45 PM",
    "total": 121,
    "available": 80,
    "blocked": 0,
    "sold": 41,
    "gross": 7995,
    "price": 195,
    "last_updated": "2026-07-10 12:21:58 PM IST"
  },
  {
    "perfIx": 125080,
    "movie": "Movie 1052",
    "venue": "B+ cinema apm (Kwun Tong)",
    "date": "2026-07-31",
    "time": "9:45 PM",
    "total": 290,
    "available": 275,
    "blocked": 0,
    "sold": 15,
    "gross": 1800,
    "price": 120,
    "last_updated": "2026-07-10 12:21:58 PM IST"
  },
  {
    "perfIx": 124980,
    "movie": "Movie 1012",
    "venue": "GALA CINEMA (Langham Place)",
    "date": "2026-07-31",
    "time": "9:50 PM",
    "total": 202,
    "available": 174,
    "blocked": 0,
    "sold": 28,
    "gross": 3920,
    "price": 140,
    "last_updated": "2026-07-10 12:21:58 PM IST"
  },
  {
    "perfIx": 125085,
    "movie": "4DX Spider-Man: Brand New Day",
    "venue": "B+ cinema apm (Kwun Tong)",
    "date": "2026-07-31",
    "time": "9:55 PM",
    "total": 52,
    "available": 20,
    "blocked": 0,
    "sold": 32,
    "gross": 6240,
    "price": 195,
    "last_updated": "2026-07-10 12:21:58 PM IST"
  },
  {
    "perfIx": 126197,
    "movie": "Movie 1055",
    "venue": "PREMIERE ELEMENTS",
    "date": "2026-07-31",
    "time": "9:55 PM",
    "total": 320,
    "available": 307,
    "blocked": 0,
    "sold": 13,
    "gross": 1820,
    "price": 140,
    "last_updated": "2026-07-10 12:21:58 PM IST"
  }
]